clyjin_templates/__init__.py
clyjin_templates/args.py
clyjin_templates/boot.py
clyjin_templates/conversion.py
clyjin_templates/filesystem/__init__.py
clyjin_templates/filesystem/maker.py
clyjin_templates/filesystem/models.py
clyjin_templates/filesystem/test_utils.py
clyjin_templates/filesystem/testing.py
clyjin_templates/modules.py
clyjin_templates/parsers.py
clyjin_templates/plugin.py
clyjin_templates/template/__init__.py
clyjin_templates/template/errors.py
clyjin_templates/template/group.py
clyjin_templates/template/group_service.py
clyjin_templates/template/refname.py
clyjin_templates/template/source.py
clyjin_templates/template/template.py
clyjin_templates/template/testing.py
clyjin_templates/template/vars.py
clyjin_templates/test_conversion.py
clyjin_templates/testing.py
clyjin_templates/utils/__init__.py
clyjin_templates/utils/klass.py
clyjin_templates/utils/never.py
clyjin_templates/utils/service.py
clyjin_templates/utils/servicehub.py
clyjin_templates/utils/singleton.py
clyjin_templates/utils/test_textvars.py
clyjin_templates/utils/textvars.py
clyjin_templates/utils/yml.py
clyjin_templates-0.1.0.dist-info/LICENSE
clyjin_templates-0.1.0.dist-info/METADATA
clyjin_templates-0.1.0.dist-info/WHEEL
clyjin_templates-0.1.0.dist-info/RECORD
