Metadata-Version: 2.1
Name: clyjin-templates
Version: 0.1.0
Summary: Creates files and directories using templates
Author: ryzhovalex
Author-email: thed4rkof@gmail.com
Requires-Python: >=3.11,<4.0
Classifier: Programming Language :: Python :: 3
Classifier: Programming Language :: Python :: 3.11
Requires-Dist: aiofiles (>=23.2.1,<24.0.0)
Requires-Dist: clyjin (>=0.2.12,<0.3.0)
Requires-Dist: mako (>=1.2.4,<2.0.0)
Requires-Dist: pyyaml (>=6.0.1,<7.0.0)
